tabulatedockerps/__init__.py
tabulatedockerps/tdps.py
tabulatedockerps-0.2.0.dist-info/LICENSE.md
tabulatedockerps-0.2.0.dist-info/METADATA
tabulatedockerps-0.2.0.dist-info/WHEEL
tabulatedockerps-0.2.0.dist-info/entry_points.txt
tabulatedockerps-0.2.0.dist-info/RECORD
