Metadata-Version: 2.3
Name: tabulatedockerps
Version: 0.2.0
Summary: Script Python que formata em tabela a saída do `docker ps`
License: MIT
Keywords: docker,tabulate,command-line,cli
Author: viniciusccosta
Author-email: viniciusccosta95@gmail.com
Requires-Python: >=3.7,<4.0
Classifier: License :: OSI Approved :: MIT License
Classifier: Programming Language :: Python :: 3
Classifier: Programming Language :: Python :: 3.7
Classifier: Programming Language :: Python :: 3.8
Classifier: Programming Language :: Python :: 3.9
Classifier: Programming Language :: Python :: 3.10
Classifier: Programming Language :: Python :: 3.11
Classifier: Programming Language :: Python :: 3.12
Classifier: Programming Language :: Python :: 3.13
Requires-Dist: tabulate (>=0.9.0,<0.10.0)
Project-URL: Homepage, https://github.com/viniciusccosta/TabulateDockerPS
Project-URL: Repository, https://github.com/viniciusccosta/TabulateDockerPS
